[
  {
    "name": "Application Start",
    "start": 1550828914563,
    "end": 1550828915311,
    "duration": 748,
    "pid": 16037,
    "index": 0
  },
  {
    "name": "Load Plugin",
    "start": 1550828914571,
    "end": 1550828914587,
    "duration": 16,
    "pid": 16037,
    "index": 1
  },
  {
    "name": "Load Config",
    "start": 1550828914588,
    "end": 1550828914610,
    "duration": 22,
    "pid": 16037,
    "index": 2
  },
  {
    "name": "Require(0) config/config.default.js",
    "start": 1550828914588,
    "end": 1550828914590,
    "duration": 2,
    "pid": 16037,
    "index": 3
  },
  {
    "name": "Require(1) node_modules/_egg-session@3.1.0@egg-session/config/config.default.js",
    "start": 1550828914591,
    "end": 1550828914591,
    "duration": 0,
    "pid": 16037,
    "index": 4
  },
  {
    "name": "Require(2) node_modules/_egg-security@2.4.3@egg-security/config/config.default.js",
    "start": 1550828914592,
    "end": 1550828914592,
    "duration": 0,
    "pid": 16037,
    "index": 5
  },
  {
    "name": "Require(3) node_modules/_egg-jsonp@2.0.0@egg-jsonp/config/config.default.js",
    "start": 1550828914593,
    "end": 1550828914594,
    "duration": 1,
    "pid": 16037,
    "index": 6
  },
  {
    "name": "Require(4) node_modules/_egg-onerror@2.1.0@egg-onerror/config/config.default.js",
    "start": 1550828914594,
    "end": 1550828914594,
    "duration": 0,
    "pid": 16037,
    "index": 7
  },
  {
    "name": "Require(5) node_modules/_egg-i18n@2.0.0@egg-i18n/config/config.default.js",
    "start": 1550828914595,
    "end": 1550828914595,
    "duration": 0,
    "pid": 16037,
    "index": 8
  },
  {
    "name": "Require(6) node_modules/_egg-watcher@3.1.0@egg-watcher/config/config.default.js",
    "start": 1550828914596,
    "end": 1550828914597,
    "duration": 1,
    "pid": 16037,
    "index": 9
  },
  {
    "name": "Require(7) node_modules/_egg-schedule@3.6.0@egg-schedule/config/config.default.js",
    "start": 1550828914597,
    "end": 1550828914597,
    "duration": 0,
    "pid": 16037,
    "index": 10
  },
  {
    "name": "Require(8) node_modules/_egg-multipart@2.4.0@egg-multipart/config/config.default.js",
    "start": 1550828914598,
    "end": 1550828914598,
    "duration": 0,
    "pid": 16037,
    "index": 11
  },
  {
    "name": "Require(9) node_modules/_egg-development@2.4.2@egg-development/config/config.default.js",
    "start": 1550828914599,
    "end": 1550828914599,
    "duration": 0,
    "pid": 16037,
    "index": 12
  },
  {
    "name": "Require(10) node_modules/_egg-logrotator@3.0.5@egg-logrotator/config/config.default.js",
    "start": 1550828914600,
    "end": 1550828914600,
    "duration": 0,
    "pid": 16037,
    "index": 13
  },
  {
    "name": "Require(11) node_modules/_egg-static@2.2.0@egg-static/config/config.default.js",
    "start": 1550828914600,
    "end": 1550828914601,
    "duration": 1,
    "pid": 16037,
    "index": 14
  },
  {
    "name": "Require(12) node_modules/_egg-view@2.1.2@egg-view/config/config.default.js",
    "start": 1550828914601,
    "end": 1550828914601,
    "duration": 0,
    "pid": 16037,
    "index": 15
  },
  {
    "name": "Require(13) node_modules/_egg-mysql@3.0.0@egg-mysql/config/config.default.js",
    "start": 1550828914602,
    "end": 1550828914603,
    "duration": 1,
    "pid": 16037,
    "index": 16
  },
  {
    "name": "Require(14) node_modules/_egg-cors@2.1.2@egg-cors/config/config.default.js",
    "start": 1550828914603,
    "end": 1550828914603,
    "duration": 0,
    "pid": 16037,
    "index": 17
  },
  {
    "name": "Require(15) node_modules/_egg@2.16.2@egg/config/config.default.js",
    "start": 1550828914604,
    "end": 1550828914604,
    "duration": 0,
    "pid": 16037,
    "index": 18
  },
  {
    "name": "Require(16) config/config.default.js",
    "start": 1550828914606,
    "end": 1550828914606,
    "duration": 0,
    "pid": 16037,
    "index": 19
  },
  {
    "name": "Require(17) node_modules/_egg-security@2.4.3@egg-security/config/config.local.js",
    "start": 1550828914606,
    "end": 1550828914607,
    "duration": 1,
    "pid": 16037,
    "index": 20
  },
  {
    "name": "Require(18) node_modules/_egg-watcher@3.1.0@egg-watcher/config/config.local.js",
    "start": 1550828914607,
    "end": 1550828914608,
    "duration": 1,
    "pid": 16037,
    "index": 21
  },
  {
    "name": "Require(19) node_modules/_egg-view@2.1.2@egg-view/config/config.local.js",
    "start": 1550828914608,
    "end": 1550828914609,
    "duration": 1,
    "pid": 16037,
    "index": 22
  },
  {
    "name": "Require(20) node_modules/_egg@2.16.2@egg/config/config.local.js",
    "start": 1550828914609,
    "end": 1550828914609,
    "duration": 0,
    "pid": 16037,
    "index": 23
  },
  {
    "name": "Load extend/application.js",
    "start": 1550828914611,
    "end": 1550828914624,
    "duration": 13,
    "pid": 16037,
    "index": 24
  },
  {
    "name": "Require(21) node_modules/_egg-session@3.1.0@egg-session/app/extend/application.js",
    "start": 1550828914611,
    "end": 1550828914612,
    "duration": 1,
    "pid": 16037,
    "index": 25
  },
  {
    "name": "Require(22) node_modules/_egg-security@2.4.3@egg-security/app/extend/application.js",
    "start": 1550828914613,
    "end": 1550828914614,
    "duration": 1,
    "pid": 16037,
    "index": 26
  },
  {
    "name": "Require(23) node_modules/_egg-jsonp@2.0.0@egg-jsonp/app/extend/application.js",
    "start": 1550828914614,
    "end": 1550828914616,
    "duration": 2,
    "pid": 16037,
    "index": 27
  },
  {
    "name": "Require(24) node_modules/_egg-logrotator@3.0.5@egg-logrotator/app/extend/application.js",
    "start": 1550828914617,
    "end": 1550828914618,
    "duration": 1,
    "pid": 16037,
    "index": 28
  },
  {
    "name": "Require(25) node_modules/_egg-view@2.1.2@egg-view/app/extend/application.js",
    "start": 1550828914619,
    "end": 1550828914620,
    "duration": 1,
    "pid": 16037,
    "index": 29
  },
  {
    "name": "Require(26) app/extend/application.js",
    "start": 1550828914620,
    "end": 1550828914624,
    "duration": 4,
    "pid": 16037,
    "index": 30
  },
  {
    "name": "Load extend/request.js",
    "start": 1550828914624,
    "end": 1550828914627,
    "duration": 3,
    "pid": 16037,
    "index": 31
  },
  {
    "name": "Require(27) node_modules/_egg@2.16.2@egg/app/extend/request.js",
    "start": 1550828914625,
    "end": 1550828914626,
    "duration": 1,
    "pid": 16037,
    "index": 32
  },
  {
    "name": "Load extend/response.js",
    "start": 1550828914627,
    "end": 1550828914630,
    "duration": 3,
    "pid": 16037,
    "index": 33
  },
  {
    "name": "Require(28) node_modules/_egg@2.16.2@egg/app/extend/response.js",
    "start": 1550828914627,
    "end": 1550828914629,
    "duration": 2,
    "pid": 16037,
    "index": 34
  },
  {
    "name": "Load extend/context.js",
    "start": 1550828914630,
    "end": 1550828914695,
    "duration": 65,
    "pid": 16037,
    "index": 35
  },
  {
    "name": "Require(29) node_modules/_egg-security@2.4.3@egg-security/app/extend/context.js",
    "start": 1550828914630,
    "end": 1550828914642,
    "duration": 12,
    "pid": 16037,
    "index": 36
  },
  {
    "name": "Require(30) node_modules/_egg-jsonp@2.0.0@egg-jsonp/app/extend/context.js",
    "start": 1550828914642,
    "end": 1550828914645,
    "duration": 3,
    "pid": 16037,
    "index": 37
  },
  {
    "name": "Require(31) node_modules/_egg-i18n@2.0.0@egg-i18n/app/extend/context.js",
    "start": 1550828914645,
    "end": 1550828914646,
    "duration": 1,
    "pid": 16037,
    "index": 38
  },
  {
    "name": "Require(32) node_modules/_egg-multipart@2.4.0@egg-multipart/app/extend/context.js",
    "start": 1550828914646,
    "end": 1550828914690,
    "duration": 44,
    "pid": 16037,
    "index": 39
  },
  {
    "name": "Require(33) node_modules/_egg-view@2.1.2@egg-view/app/extend/context.js",
    "start": 1550828914690,
    "end": 1550828914692,
    "duration": 2,
    "pid": 16037,
    "index": 40
  },
  {
    "name": "Require(34) node_modules/_egg@2.16.2@egg/app/extend/context.js",
    "start": 1550828914692,
    "end": 1550828914693,
    "duration": 1,
    "pid": 16037,
    "index": 41
  },
  {
    "name": "Load extend/helper.js",
    "start": 1550828914695,
    "end": 1550828914716,
    "duration": 21,
    "pid": 16037,
    "index": 42
  },
  {
    "name": "Require(35) node_modules/_egg-security@2.4.3@egg-security/app/extend/helper.js",
    "start": 1550828914695,
    "end": 1550828914714,
    "duration": 19,
    "pid": 16037,
    "index": 43
  },
  {
    "name": "Require(36) node_modules/_egg@2.16.2@egg/app/extend/helper.js",
    "start": 1550828914715,
    "end": 1550828914716,
    "duration": 1,
    "pid": 16037,
    "index": 44
  },
  {
    "name": "Load app.js",
    "start": 1550828914717,
    "end": 1550828914773,
    "duration": 56,
    "pid": 16037,
    "index": 45
  },
  {
    "name": "Require(37) node_modules/_egg-session@3.1.0@egg-session/app.js",
    "start": 1550828914717,
    "end": 1550828914717,
    "duration": 0,
    "pid": 16037,
    "index": 46
  },
  {
    "name": "Require(38) node_modules/_egg-security@2.4.3@egg-security/app.js",
    "start": 1550828914718,
    "end": 1550828914720,
    "duration": 2,
    "pid": 16037,
    "index": 47
  },
  {
    "name": "Require(39) node_modules/_egg-onerror@2.1.0@egg-onerror/app.js",
    "start": 1550828914720,
    "end": 1550828914735,
    "duration": 15,
    "pid": 16037,
    "index": 48
  },
  {
    "name": "Require(40) node_modules/_egg-i18n@2.0.0@egg-i18n/app.js",
    "start": 1550828914735,
    "end": 1550828914741,
    "duration": 6,
    "pid": 16037,
    "index": 49
  },
  {
    "name": "Require(41) node_modules/_egg-watcher@3.1.0@egg-watcher/app.js",
    "start": 1550828914742,
    "end": 1550828914747,
    "duration": 5,
    "pid": 16037,
    "index": 50
  },
  {
    "name": "Require(42) node_modules/_egg-schedule@3.6.0@egg-schedule/app.js",
    "start": 1550828914747,
    "end": 1550828914750,
    "duration": 3,
    "pid": 16037,
    "index": 51
  },
  {
    "name": "Require(43) node_modules/_egg-multipart@2.4.0@egg-multipart/app.js",
    "start": 1550828914750,
    "end": 1550828914754,
    "duration": 4,
    "pid": 16037,
    "index": 52
  },
  {
    "name": "Require(44) node_modules/_egg-development@2.4.2@egg-development/app.js",
    "start": 1550828914754,
    "end": 1550828914755,
    "duration": 1,
    "pid": 16037,
    "index": 53
  },
  {
    "name": "Require(45) node_modules/_egg-logrotator@3.0.5@egg-logrotator/app.js",
    "start": 1550828914755,
    "end": 1550828914755,
    "duration": 0,
    "pid": 16037,
    "index": 54
  },
  {
    "name": "Require(46) node_modules/_egg-static@2.2.0@egg-static/app.js",
    "start": 1550828914755,
    "end": 1550828914756,
    "duration": 1,
    "pid": 16037,
    "index": 55
  },
  {
    "name": "Require(47) node_modules/_egg-mysql@3.0.0@egg-mysql/app.js",
    "start": 1550828914756,
    "end": 1550828914772,
    "duration": 16,
    "pid": 16037,
    "index": 56
  },
  {
    "name": "Require(48) node_modules/_egg-cors@2.1.2@egg-cors/app.js",
    "start": 1550828914772,
    "end": 1550828914772,
    "duration": 0,
    "pid": 16037,
    "index": 57
  },
  {
    "name": "Before Start in node_modules/_egg-watcher@3.1.0@egg-watcher/lib/init.js:15:14",
    "start": 1550828914791,
    "end": 1550828915041,
    "duration": 250,
    "pid": 16037,
    "index": 58
  },
  {
    "name": "Before Start in node_modules/_egg-mysql@3.0.0@egg-mysql/lib/mysql.js:20:7",
    "start": 1550828914918,
    "end": 1550828915032,
    "duration": 114,
    "pid": 16037,
    "index": 59
  },
  {
    "name": "Load Service",
    "start": 1550828914918,
    "end": 1550828914922,
    "duration": 4,
    "pid": 16037,
    "index": 60
  },
  {
    "name": "Load \"service\" to Context",
    "start": 1550828914918,
    "end": 1550828914922,
    "duration": 4,
    "pid": 16037,
    "index": 61
  },
  {
    "name": "Load Middleware",
    "start": 1550828914922,
    "end": 1550828915014,
    "duration": 92,
    "pid": 16037,
    "index": 62
  },
  {
    "name": "Load \"middlewares\" to Application",
    "start": 1550828914923,
    "end": 1550828915005,
    "duration": 82,
    "pid": 16037,
    "index": 63
  },
  {
    "name": "Load Controller",
    "start": 1550828915014,
    "end": 1550828915016,
    "duration": 2,
    "pid": 16037,
    "index": 64
  },
  {
    "name": "Load \"controller\" to Application",
    "start": 1550828915015,
    "end": 1550828915016,
    "duration": 1,
    "pid": 16037,
    "index": 65
  },
  {
    "name": "Load Router",
    "start": 1550828915016,
    "end": 1550828915018,
    "duration": 2,
    "pid": 16037,
    "index": 66
  },
  {
    "name": "Require(49) app/router.js",
    "start": 1550828915016,
    "end": 1550828915017,
    "duration": 1,
    "pid": 16037,
    "index": 67
  },
  {
    "name": "Before Start in node_modules/_egg-core@4.14.1@egg-core/lib/egg.js:303:10",
    "start": 1550828915017,
    "end": 1550828915034,
    "duration": 17,
    "pid": 16037,
    "index": 68
  },
  {
    "name": "Before Start in app/router.js:15:7",
    "start": 1550828915018,
    "end": 1550828915309,
    "duration": 291,
    "pid": 16037,
    "index": 69
  },
  {
    "name": "Before Start in node_modules/_egg-mysql@3.0.0@egg-mysql/lib/mysql.js:20:7",
    "start": 1550828915032,
    "end": 1550828915213,
    "duration": 181,
    "pid": 16037,
    "index": 70
  }
]